discord_to_authentik/__init__.py
discord_to_authentik/main.py
discord_to_authentik/setup.py
discord_to_authentik-0.1.2.dist-info/LICENSE.md
discord_to_authentik-0.1.2.dist-info/METADATA
discord_to_authentik-0.1.2.dist-info/WHEEL
discord_to_authentik-0.1.2.dist-info/entry_points.txt
discord_to_authentik-0.1.2.dist-info/RECORD
